kani/ext/vllm/__init__.py
kani/ext/vllm/bases.py
kani/ext/vllm/engine.py
kani/ext/vllm/http_engine.py
kani/ext/vllm/openai_compat_engine.py
kani/ext/vllm/utils.py
kani/ext/vllm/vllm_server.py
kani_ext_vllm-0.2.2.dist-info/METADATA
kani_ext_vllm-0.2.2.dist-info/WHEEL
kani_ext_vllm-0.2.2.dist-info/licenses/LICENSE
kani_ext_vllm-0.2.2.dist-info/RECORD
