Metadata-Version: 2.4
Name: kani-ext-vllm
Version: 0.2.2
Summary: vLLM backend for kani
Project-URL: Homepage, https://github.com/zhudotexe/kani-ext-vllm
Project-URL: Bug Tracker, https://github.com/zhudotexe/kani-ext-vllm/issues
Author-email: Andrew Zhu <andrew@zhu.codes>
License: MIT License
License-File: LICENSE
Classifier: Intended Audience :: Science/Research
Classifier: License :: OSI Approved :: MIT License
Classifier: Operating System :: OS Independent
Classifier: Programming Language :: Python :: 3
Classifier: Topic :: Scientific/Engineering :: Artificial Intelligence
Requires-Python: >=3.10
Requires-Dist: kani<2.0.0,>=1.7.0
Requires-Dist: vllm<1.0.0,>=0.11.0
